argdeco.py
argdeco_josugoar-1.6.0.dist-info/LICENSE
argdeco_josugoar-1.6.0.dist-info/METADATA
argdeco_josugoar-1.6.0.dist-info/WHEEL
argdeco_josugoar-1.6.0.dist-info/top_level.txt
argdeco_josugoar-1.6.0.dist-info/RECORD
