Metadata-Version: 2.1
Name: argdeco-josugoar
Version: 1.6.0
Summary: Opinionated argparse wrapper
Home-page: https://github.com/josugoar/argdeco
Download-URL: https://github.com/josugoar/argdeco/archive/v1.6.0.tar.gz
Author: josugoar
License: MIT
Project-URL: Source, https://github.com/josugoar/argdeco
Keywords: argparse cli docker library python
Classifier: Development Status :: 5 - Production/Stable
Classifier: Environment :: Console
Classifier: Intended Audience :: Developers
Classifier: License :: OSI Approved :: MIT License
Classifier: Operating System :: OS Independent
Classifier: Programming Language :: Python :: 3.9
Classifier: Programming Language :: Python :: 3.10
Classifier: Programming Language :: Python :: 3.11
Classifier: Topic :: Software Development :: Libraries :: Python Modules
Requires-Python: >=3.9
License-File: LICENSE
